gefran-pid/__init__.py
gefran-pid/__version__.py
gefran-pid/errors.py
gefran-pid/pid.py
gefran_pid/__init__.py
gefran_pid/__version__.py
gefran_pid/errors.py
gefran_pid/pid.py
gefran_pid-0.1.0.dist-info/METADATA
gefran_pid-0.1.0.dist-info/WHEEL
gefran_pid-0.1.0.dist-info/top_level.txt
gefran_pid-0.1.0.dist-info/RECORD
