Metadata-Version: 2.1
Name: gefran-pid
Version: 0.1.0
Summary: Unofficial package to control a Gefran PID controller (with Modbus RTU) in Python. Not affiliated with Gefran.
Home-page: https://github.com/thvranken/gefran_pid
Author: Thomas Vranken
Author-email: thvranken@gmail.com
License: GNU
Download-URL: https://pypi.org/project/gefran-pid/
Keywords: Gefran,PID,Temperature
Platform: UNKNOWN
Requires-Python: >=3.6
Requires-Dist: hein-utilities
Requires-Dist: numpy
Requires-Dist: modbus-tk
Requires-Dist: pyserial
